MANIFEST.in
README.txt
setup.cfg
setup.py
aws/__init__.py
aws/__init__.pyc
aws.windowsplonecluster.egg-info/PKG-INFO
aws.windowsplonecluster.egg-info/SOURCES.txt
aws.windowsplonecluster.egg-info/dependency_links.txt
aws.windowsplonecluster.egg-info/entry_points.txt
aws.windowsplonecluster.egg-info/namespace_packages.txt
aws.windowsplonecluster.egg-info/not-zip-safe
aws.windowsplonecluster.egg-info/requires.txt
aws.windowsplonecluster.egg-info/top_level.txt
aws/windowsplonecluster/README.txt
aws/windowsplonecluster/__init__.py
aws/windowsplonecluster/interfaces.py
aws/windowsplonecluster/tests.py
aws/windowsplonecluster/utils.py
docs/HISTORY.txt
docs/config.ini
docs/source/configuration.rst
docs/source/execution.rst
docs/source/index.rst
docs/source/installation.rst