Metadata-Version: 1.0
Name: aws.windowsplonecluster
Version: 0.8
Summary: A super script to control a zope/apache/pound/squid cluster for windows
Home-page: https://github.com/yboussard/aws.windowsplonecluster
Author: Youenn Boussard
Author-email: youenn.boussard@alterway.fr
License: GPL
Keywords: windows service pound zope
Platform: UNKNOWN
Classifier: Programming Language :: Python
Classifier: Topic :: Software Development :: Libraries :: Python Modules
